plasmiduncover
