Metadata-Version: 1.0
Name: plasmiduncover
Version: 1.0.4
Summary: Script to obtain plasmid id from WGS data using bowtie2 to map
Home-page: https://github.com/tiagofilipe12/PlasmidCoverage
Author: Tiago F. Jesus
Author-email: tiagojesus@medicina.ulisboa.pt
License: GPL3
Platform: UNKNOWN
